Workbook

Sheet SUMMARY
A1: PURCHASES & EXPENSES 2026 — WORKBOOK SUMMARY
A2: Source file: purchase et expenses 2026 Bea.xlsx | Currency: RWF | All dates displayed as DD/MM/YYYY
A4: 1. WHAT THIS WORKBOOK CONTAINS
A5: Sheet | B5: Period covered | C5: Rows of data | D5: Status | E5: Contents
A6: JAN FEB MARC | B6: Jan–Mar 2026 | C6: 301 | D6: Complete | E6: Daily purchase/expense register + 3 monthly VAT blocks (sales, VAT recovered EBM, VAT sent, VAT to pay)
A7: APRIL, MAY JUN | B7: Apr–Jun 2026 | C7: 352 | D7: Complete | E7: Same structure as Q1: purchase register + 4 VAT computation blocks
A8: JULY AUG SEPT | B8: Jul–Sep 2026 | C8: 349 | D8: Repaired | E8: Purchase register + VAT blocks; 3 VAT-to-pay formulas were broken (#REF!) and have been rebuilt
A9: OCT NOV DEC | B9: Oct–Dec 2026 | C9: 0 | D9: EMPTY — to be filled | E9: Formatting only, no data yet. Q4 must be entered before the annual report is final
A10: ANNUAL REPORT | B10: Jan–Jun 2026 | C10: 170 | D10: Repaired | E10: Supplier-level purchase listing by month (TIN, supplier, goods, EBM receipt no., date, amount excl. VAT, VAT)
A11: IBIKENEWE MU KWIGA | B11: Requisition (dated 06/07/2025) | C11: 47 | D11: Repaired | E11: Requisition / stock roll-forward: qty x price, purchases, closing stock. 4 #VALUE! errors fixed
A12: control formule | B12: n/a | C12: 44 | D12: Working scratchpad | E12: Ad-hoc quantity x price checks and manual cross-checks; not part of the reporting chain
A13: UNCONTROLED | B13: Annual | C13: 9 | D13: Complete | E13: Uncontrolled / unsupported expense list (incl. an annualised 30,000 x 12 item)
A16: 2. PURCHASES & EXPENSES BY MONTH (from ANNUAL REPORT)
A17: Month | B17: Amount excl. VAT | C17: VAT | D17: Total incl. VAT | E17: Source cells
A18: January 2026 | B18: ='ANNUAL REPORT'!G39-C18 -> 17678888 | C18: =SUM('ANNUAL REPORT'!F1:F38) -> 890944 | D18: ='ANNUAL REPORT'!G39 -> 18569832 | E18: ANNUAL REPORT rows 1-39 (col G gross, col F VAT)
A19: February 2026 | B19: ='ANNUAL REPORT'!F48 -> 11564800 | C19: 0 | D19: =B19+C19 -> 11564800 | E19: ANNUAL REPORT F48 (no VAT recorded on these lines)
A20: March 2026 | B20: ='ANNUAL REPORT'!F59 -> 7065152.5 | C20: ='ANNUAL REPORT'!G54 -> 152847.46 | D20: =B20+C20 -> 7218000 | E20: ANNUAL REPORT F59 / G54
A21: April 2026 | B21: ='ANNUAL REPORT'!F86 -> 11872522 | C21: ='ANNUAL REPORT'!G74 -> 99696.97 | D21: =B21+C21 -> 11972219 | E21: ANNUAL REPORT F86 / G74
A22: May 2026 | B22: ='ANNUAL REPORT'!F121 -> 3516620.5 | C22: ='ANNUAL REPORT'!G114 -> 402609.59 | D22: =B22+C22 -> 3919230.1 | E22: ANNUAL REPORT F121 / G114
A23: June 2026 | B23: ='ANNUAL REPORT'!F170 -> 4406817.3 | C23: ='ANNUAL REPORT'!G157 -> 345905.4 | D23: =B23+C23 -> 4752722.7 | E23: ANNUAL REPORT F170 / G157
A24: TOTAL H1 2026 | B24: =SUM(B18:B23) -> 56104801 | C24: =SUM(C18:C23) -> 1892003.4 | D24: =SUM(D18:D23) -> 57996804 | E24: Jul-Dec 2026 not yet carried into ANNUAL REPORT
A27: 3. VAT DECLARATION BLOCKS (VAT recovered less VAT invoiced)
A28: Month labels beside these blocks are inconsistent in the source sheets — confirm the declaration period before filing.
A29: Sheet | B29: Block (source cell) | C29: VAT to pay / (credit) | E29: Note
A30: JAN FEB MARC | B30: Block 1 — G66 | C30: ='JAN FEB MARC'!G66 -> 24907 | E30: Labelled FEVRIER 2026 in source
A31: JAN FEB MARC | B31: Block 2 — G127 | C31: ='JAN FEB MARC'!G127 -> 66483 | E31: Labelled MARS 2026 in source
A32: JAN FEB MARC | B32: Block 3 — G175 | C32: ='JAN FEB MARC'!G175 -> -43481 | E32: Credit position (negative)
A33: APRIL, MAY JUN | B33: Block 1 — G55 | C33: ='APRIL, MAY JUN'!G55 -> -44966 | E33: Credit position (negative)
A34: APRIL, MAY JUN | B34: Block 2 — G109 | C34: ='APRIL, MAY JUN'!G109 -> -146503 | E34: Credit position (negative)
A35: APRIL, MAY JUN | B35: Block 3 — G179 | C35: ='APRIL, MAY JUN'!G179 -> -277473 | E35: Marked “REFUND JUNE” in source
A36: APRIL, MAY JUN | B36: Block 4 — G226 | C36: ='APRIL, MAY JUN'!G226 -> 3294175 | E36: Same sales/VAT figures as JULY AUG SEPT block 4 — possible duplicated block
A37: JULY AUG SEPT | B37: Block 1 — F55 | C37: ='JULY AUG SEPT '!F55 -> 154401 | E37: Intact in source
A38: JULY AUG SEPT | B38: Block 2 — F109 | C38: ='JULY AUG SEPT '!F109 -> 2943358.5 | E38: REBUILT (was #REF!) — VAT-recovered rows were blank; now derived from sales at 18/118
A39: JULY AUG SEPT | B39: Block 3 — F176 | C39: ='JULY AUG SEPT '!F176 -> 289793.53 | E39: REBUILT (was #REF!)
A40: JULY AUG SEPT | B40: Block 4 — F223 | C40: ='JULY AUG SEPT '!F223 -> 3294175.4 | E40: REBUILT (was #REF!)
A41: OCT NOV DEC | B41: — | C41: 0 | E41: Sheet is empty; no Q4 VAT blocks exist yet
A44: 4. AUDIT LOG — ISSUES FOUND
A45: Sheet | B45: Cells | C45: Severity | D45: Action | E45: Issue
A46: ANNUAL REPORT | B46: F59, F86, F121, F170 | C46: Critical | D46: FIXED | E46: Monthly totals summed a VAT subtotal line sitting in the Amount column — Mar/Apr/May/Jun were overstated by 152,847 / 99,697 / 402,610 / 345,905
A47: JULY AUG SEPT | B47: F109, F176, F223 (+F178) | C47: Critical | D47: FIXED | E47: VAT-to-pay formulas read =#REF!-... ; rebuilt as TOTAL VAT recovered less VAT invoiced, with D106/D107, D173/D174, D220/D221 derived from sales at 18/118
A48: IBIKENEWE MU KWIGA | B48: G7, G9, G10, I9, I10 | C48: Critical | D48: FIXED | E48: VALUE errors — stock roll-forward subtracted column F, which holds item names (text). Now uses SUM(F..) so text is ignored
A49: Whole workbook | B49: ~1,500 cells | C49: Warning | D49: FIXED | E49: All date cells standardised to DD/MM/YYYY; 108 dates stored as text (incl. 103 in ANNUAL REPORT col E) converted to real dates
A50: OCT NOV DEC | B50: Entire sheet | C50: Critical | D50: OPEN | E50: No data at all — Q4 purchases and VAT blocks must be entered before an annual report can be produced
A51: ANNUAL REPORT | B51: F54, F74, F114, F157 | C51: Warning | D51: OPEN | E51: VAT subtotals typed as static numbers into the Amount column; left in place but excluded from the totals. Better to delete them or link to G54/G74/G114/G157
A52: ANNUAL REPORT / APRIL, MAY JUN | B52: F85 / G45 | C52: Warning | D52: OPEN | E52: =1522*600 — quantity and unit price buried inside a formula; should sit in their own cells
A53: JAN FEB MARC | B53: D52:D53, E63:E64, E124:E125 pattern | C53: Warning | D53: OPEN | E53: VAT-recovered rows retyped as rounded constants instead of linking to the 18/118 calculation above — small rounding differences in VAT to pay
A54: APRIL, MAY JUN / JULY AUG SEPT | B54: G226 / F223 blocks | C54: Warning | D54: OPEN | E54: Identical sales and VAT figures appear in a block on both sheets — confirm this is not a duplicated declaration
A55: ANNUAL REPORT | B55: A5 | C55: Info | D55: OPEN | E55: Date reads 13/01/2025 (RIJE LTD line) inside a 2026 register — likely a typing error
A56: UNCONTROLED / control formule | B56: — | C56: Info | D56: OPEN | E56: Working sheets with hardcoded arithmetic (=30000*12, =72*150); not linked to any statement

Sheet JAN FEB MARC
B2: JANVIER 2026
A3: date | B3: company tin | C3: company name | D3: items | E3: facture no | F3: vat sent | G3: total amount
A4: 46028 | C4: INNOPRO LTD | D4: SUGER | F4: 1037000 | G4: 6800000
A5: 46035 | C5: EASTERN HOPE SHOP LTD | D5: SUGER | F5: 1022034 | G5: 6700000
A6: 46044 | C6: HOZINEZA SHOP LTD | D6: SUGER | F6: 1000678 | G6: 6560000
A7: 46027 | C7: VPLUS PACKAGING INDUSTRIES LTD | D7: CARTONS | F7: 290395 | G7: 1903699
F8: =SUM(F4:F7) -> 3350107 | G8: =SUM(G4:G7) -> 21963699
B11: IZISIGAYE ZOSE NI DEPENSES
A13: 46039 | C13: PLAN ONE SUPPLY LTD | D13: IBIKORESHO BYO KUBAKA | F13: 508576 | G13: 3334000
A14: 46044 | C14: MINI IMPRIMERIES BLESSING | D14: PAPIER ENVELOPPES | F14: 62542 | G14: 410000 | H14: ISUKARI | I14: 6800000
A15: 46038 | C15: MINI IMPRIMERIES BLESSING | D15: PAPIER ENVELOPPES | F15: 46067 | G15: 302000 | I15: 6700000
A16: 46028 | C16: REG | D16: UMURIRO | E16: 50000 | F16: 30508 | G16: 200000 | I16: 6560000
A17: 45670 | C17: RIJE LTD | D17: DIFFERENT GOODS | F17: 25916 | G17: 200000 | H17: IBINYAMPEKE | I17: 2000000
A18: 46032 | C18: MINI IMPRIMERIES BLESSING | D18: PAPIER ENVELOPPES | F18: 22729 | G18: 149000 | I18: 4040000
A19: 46041 | C19: CPS LUBRICANT LTD | D19: HELIOS SAE | F19: 18305 | G19: 120000 | I19: 5200000
A20: 46027 | C20: AKOMBONYE COMPANY LTD | D20: WOODFIX | F20: 12600 | G20: 82600 | I20: 1435000
A21: 46050 | C21: CHAMPION TECHNOLOGIES LTD | D21: INK | F21: 1220 | G21: 8000 | I21: =SUM(I14:I20) -> 32735000
A22: 46042 | C22: IKAMBA GENERAL TRADING &SUPPLY CO LTD | D22: PRINT CERTIFICATES | F22: 6102 | G22: 40000 | H22: SALES | I22: =C60 -> 21984200
A23: 46050 | C23: REG | D23: UMURIRO | F23: 3043 | G23: 20000
A24: 46029 | C24: AGRUNI LTD | D24: WASTE COLLECTION SRV | G24: 24000 | H24: DIFFERENCE | I24: =I21-I22 -> 10750800
H25: IBITARACURUZWA
G27: =SUM(G13:G26) -> 4889600
A28: 46035 | C28: SP NYIRANGARAMA | D28: ESSANCES | F28: 11180 | G28: 73295
A29: 46043 | C29: SP NYIRANGARAMA | D29: ESSANCES | F29: 10825 | G29: 70968
A30: 46027 | B30: 103582274 | C30: SP NYIRANGARAMA | D30: ESSANCES | F30: 10312 | G30: 67606
A31: 46032 | C31: SP NYIRANGARAMA | D31: ESSANCES | F31: 9867 | G31: 64682
A32: 46037 | C32: SP NYIRANGARAMA | D32: ESSANCES | F32: 9660 | G32: 63330
A33: 46039 | C33: SP NYIRANGARAMA | D33: ESSANCES | F33: 9226 | G33: 60485
A34: 46049 | C34: SP NYIRANGARAMA | D34: ESSANCES | F34: 8428 | G34: 55254
A35: 46029 | C35: SP NYIRANGARAMA | D35: ESSANCES | F35: 8049 | G35: 52768
A36: 46028 | C36: SP NYIRANGARAMA | D36: ESSANCES | F36: 7958 | G36: 52171
A37: 46030 | C37: SP NYIRANGARAMA | D37: ESSANCES | F37: 7833 | G37: 51356
A38: 46034 | C38: SP NYIRANGARAMA | D38: ESSANCES | F38: 6899 | G38: 45230
A39: 46051 | C39: SP NYIRANGARAMA | D39: ESSANCES | F39: 6884 | G39: 45130
A40: 46025 | B40: 103582274 | C40: SP NYIRANGARAMA | D40: ESSANCES | F40: 6762 | G40: 44335
A41: 46039 | C41: SP NYIRANGARAMA | D41: ESSANCES | F41: 6733 | G41: 44136
A42: 46024 | B42: 103582274 | C42: SP NYIRANGARAMA | D42: ESSANCES | F42: 6374 | G42: 41769
A43: 46031 | C43: SP NYIRANGARAMA | D43: ESSANCES | F43: 5252 | G43: 34430
A44: 46037 | C44: SP NYIRANGARAMA | D44: ESSANCES | F44: 4575 | G44: 30000
A45: 46050 | C45: SP NYIRANGARAMA | D45: ESSANCES | F45: 4554 | G45: 29855
A46: 46050 | C46: SP NYIRANGARAMA | D46: ESSANCES | F46: 4554 | G46: 29855
A47: 46034 | C47: SP NYIRANGARAMA | D47: ESSANCES | F47: 3052 | G47: 20000
A48: 46040 | C48: SP NYIRANGARAMA | D48: ESSANCES | F48: 2833 | G48: 18577
A49: 46036 | C49: SP NYIRANGARAMA | D49: ESSANCES | F49: 1526 | G49: 10000
G50: =SUM(G28:G49) -> 1005232
A51: 46030 | C51: BATTISTA BUSINESS | D51: IBIGORI | G51: 4040000
A52: 46043 | C52: BATTISTA BUSINESS | D52: SOYA NÍBIGORI | G52: 5200000
A53: 46043 | C53: GACAMUMANZA | D53: IBIGORI | G53: 1435000
A54: 46029 | C54: MAGENDU PONTIEN | D54: IBIGORI | G54: 2000000
G55: =SUM(G51:G54) -> 12675000
A56: TOTAL | F56: =F8 -> 3350107 | G56: =G8+G27+G50+G55 -> 40533531
B58: SALES BRANCH 01 | D58: 20820100 | E58: =D58*18/118 -> 3175947.5
B59: SALES BASE | D59: 1164100 | E59: =D59*18/118 -> 177574.58 | H59: 24675
C60: =D58+D59 -> 21984200 | E60: =D60*18/118 -> 0 | H60: VAT PAID
B61: VAT MANAGEMENT | E61: VAT RECEIVED EBM | F61: VAT SENT FACT | G61: VAT TO PAY
B63: VAT BRANCH01 REC | E63: 3172286
B64: VAT BASE REC | E64: 202728
B66: TOTAL | E66: =SUM(E63:E65) -> 3375014 | F66: =F56 -> 3350107 | G66: =E66-F66 -> 24907 | H66: VAT TO PAY
G67: WORD
B68: FACTURE ZIKENEWE | E68: =G66*118/18 -> 163279.22 | H68: ISUKARI | I68: 6700000
I69: 6500000
I70: 3000000
H71: IBINYAMPEKE | I71: 4650000
B72: FEVRIER 2026 | I72: 4850000
I73: 757000
B74: 46063 | C74: INNOPRO LTD | D74: SUGER | F74: 1022034 | G74: 6700000 | I74: 757000
B75: 46072 | C75: INNOPRO LTD | D75: SUGER | F75: 991525 | G75: 6500000 | I75: 529300
B76: 46076 | C76: INNOPRO LTD | D76: SUGER | F76: 457627 | G76: 3000000 | H76: TOTAL | I76: =SUM(I68:I75) -> 27743300
B77: 46057 | C77: V PLUS PACKAGING ONDUSTRIES | D77: CORRUGATED CARTONS | F77: 297986 | G77: 1953464 | H77: SALES | I77: =C121 -> 21457750
B78: 46071 | C78: PLAN ONE SUPPLY LTD | D78: KUBAKA | F78: 78864 | G78: 517000 | H78: DIFFERENCES | I78: =I77-I76 -> -6285550
B79: 46069 | C79: MINI IMPRIMERIE BLESSING LRD | D79: PAPIER ENVELOPPES | F79: 63549 | G79: 416000
B80: 46081 | C80: REG | D80: UMURIRO | F80: 45763 | G80: 300000
B81: 46081 | C81: REG | D81: UMURIRO | F81: 22881 | G81: 150000
B82: 46079 | C82: AKOMBONYE COMPANY LTD | D82: KUBAKA | F82: 18991 | G82: 124500
B83: 46062 | C83: SP NYIRANGARAMA | D83: ESSANCES | F83: 13732 | G83: 90022
B84: 46072 | C84: HATUNGURAMYE | D84: PNEUS | F84: 13119 | G84: 86000
B85: 46074 | C85: SP NYIRANGARAMA | D85: ESSANCES | F85: 12967 | G85: 85010
B86: 46065 | C86: SP NYIRANGARAMA | D86: ESSANCES | F86: 10989 | G86: 72042
B87: 46069 | C87: SP NYIRANGARAMA | D87: ESSANCES | F87: 10255 | G87: 67228
B88: 46056 | C88: SP NYIRANGARAMA | D88: ESSANCES | F88: 10036 | G88: 65796
B89: 46064 | C89: SP NYIRANGARAMA | D89: ESSANCES | F89: 9857 | G89: 64623
B90: 46073 | C90: SP NYIRANGARAMA | D90: ESSANCES | F90: 9784 | G90: 64145
... B110: 46076 | C110: SP NYIRANGARAMA | D110: ESSANCES | F110: 1250 | G110: 8195
B111: 46055 | C111: RWEMA AGRI BUSINESS | D111: URUDODO | G111: 21000
B112: 46059 | C112: BATTISTA BUSINESS LTD | D112: IBIGORI SOYA | G112: 4850000
B113: 46066 | C113: BATTISTA BUSINESS LTD | D113: IBIGORI SOYA | G113: 4650000
B114: 46064 | C114: NTAGANDA ERASTE | D114: AMASAKA | G114: 757500
B115: 46065 | C115: NTAGANDA ERASTE | D115: AMASAKA | G115: 757000
B116: 46069 | C116: ANGE FAMILY BUSINESS COMPANY LTD | D116: UBURO | G116: 100000
B117: 46072 | C117: SERAGRAMS LTD | D117: SOYA | G117: 429300
B119: SALES BRANCH 01 | D119: 19295750 | E119: =D119*18/118 -> 2943419.5
B120: SALES BASE | D120: 2162000 | E120: =D120*18/118 -> 329796.61
C121: =D119+D120 -> 21457750 | E121: =D121*18/118 -> 0 | F121: =SUM(F73:F120) -> 3200707
B122: VAT MANAGEMENT | E122: VAT RECEIVED EBM | F122: VAT SENT FACT | G122: VAT TO PAY
B124: VAT BRANCH01 REC | E124: 2943419
B125: VAT BASE REC | E125: 323771
B127: TOTAL | E127: =SUM(E124:E126) -> 3267190 | F127: =F121 -> 3200707 | G127: =E127-F127 -> 66483 | H127: VAT TO BE PAID
B129: FACTURE ZIKENEWE | E129: =G127*118/18 -> 435833
B131: MARS 2026
B132: 46093 | C132: INNOPRO LTD | D132: SUGER | F132: 915254 | G132: 6000000
...

Sheet control formule
K2: AMADENI YO KURI TERRAIN RICHARD
J4: ITARIKI | K4: AHANTU | L4: AMAZINA | M4: IDENI
J5: 46031 | L5: JEANNETTE | M5: 435000
C6: manifesto | J6: 46032 | K6: KIGALI | L6: PETER DIDOS | M6: 15000
A7: 119 | B7: 14500 | C7: =A7*B7 -> 1725500 | E7: =C19 -> 1945500 | J7: 46070 | K7: MUSANZE | L7: CLARISSE | M7: 6500
A8: 0 | B8: 14500 | C8: =A8*B8 -> 0 | G8: depenses | J8: 46106 | L8: PAUL | M8: 15000 | N8: 46111
A9: 0 | B9: 15000 | C9: =A9*B9 -> 0 | E9: a verser | G9: 10500 | J9: 46112 | K9: MUSANZE | L9: CONSTANTIN | M9: 45000-32600 | N9: 46118
A10: 0 | B10: 6200 | C10: =A10*B10 -> 0 | E10: =E7-G16 -> 1401500 | G10: 26000 | J10: 46141 | K10: MUSANZE | L10: PAUL | M10: 90000
A11: 0 | B11: 6500 | C11: =A11*B11 -> 0 | F11: 0 | G11: 115500 | J11: 46090 | K11: KIGALI | L11: ROGER | M11: 145000-69000-45000-32500 | N11: 11/03,23/03,19/04/ | O11: RESTE 500
A12: 0 | B12: 4500 | C12: =A12*B12 -> 0 | E12: 632000 | G12: 296000 | J12: 46122 | K12: MUSANZE | L12: ERIC | M12: 30000-12000 | N12: 46134
A13: 0 | B13: 1208 | C13: =A13*B13 -> 0 | E13: 769500 | G13: 96000 | K13: MUSANZE | L13: JMV | M13: 14500
A14: 0 | B14: 2500 | C14: =A14*B14 -> 0 | E14: 0 | G14: 0 | J14: 46135 | K14: KIGALI | L14: THEONESTE | M14: 12000
A15: =SUM(A7:A14) -> 119 | C15: 60000 | E15: 0 | G15: 0 | J15: 46128 | K15: MUSANZE | L15: PETER | M15: 8000
C16: 72500 | D16: diff | E16: =E10-E12-E13-E14 -> 0 | G16: =SUM(G9:G15) -> 544000 | H16: 0 | J16: 46146 | K16: KIGALI | L16: FERDINAND/ KWISHYURA | M16: 30000
C17: 87500 | H17: =G16-H16 -> 544000 | J17: 46174 | L17: MOISE/ KWISHYURA | M17: 150000
C18: 0 | J18: 46148 | K18: GICUMBI | L18: JEANNETTE | M18: 19500
B19: ventes | C19: =SUM(C7:C18) -> 1945500 | J19: 46157 | K19: RUBAVU | L19: CLAUDE | M19: 300000-150000 | N19: 46164
J20: 46168 | K20: MUSANZE | L20: XAVIER | M20: 217500-130000 | N20: 46171
F21: 590000 | G21: 8800 | H21: =72*150 -> 10800 | J21: 46171 | K21: MUSANZE | L21: ANNANIAS | M21: 58500
F22: 662500 | G22: 9 | J22: 46171 | K22: KIGALI | L22: PAUL | M22: 140000-100000 | N22: 46175
F23: 0 | J23: 46174
F24: 0 | L24: ROGER | M24: 116000
F25: 0 | L25: NIYONSENGA | M25: 12500
F26: =SUM(F21:F25) -> 1252500
I29: 2026

Sheet IBIKENEWE MU KWIGA
B4: REQUISITION FORM
A5: DATE | B5: AMAZINA | C5: INGANO KG | D5: IGICIRO | E5: TOTAL | F5: IBYAGUZWE | G5: INGANO | H5: IBICIRO | I5: TOTAL | J5: IBISIGAYE | K5: INGANO | L5: IGICIRO | M5: TOTAL
A6: 45838 | B6: IBIGORI | C6: 3000 | D6: 500 | E6: =C6*D6 -> 1500000 | F6: IBIGORI | I6: =G6*H6 -> 0 | M6: =K6*L6 -> 0
B7: SOYA | C7: 600 | D7: 900 | E7: =C7*D7 -> 540000 | G7: =G6+E7-SUM(F7) -> 540000 | I7: =G7*H7 -> 0 | M7: =K7*L7 -> 0
B8: AMASAKA | C8: 2000 | D8: 650 | E8: =C8*D8 -> 1300000 | F8: AMASAKA | G8: 1600 | H8: 560 | I8: =G8*H8 -> 896000 | M8: =K8*L8 -> 0
B9: INGANO | C9: 500 | D9: 800 | E9: =C9*D9 -> 400000 | F9: INGANO | G9: =G8+E9-SUM(F9) -> 401600 | I9: =G9*H9 -> 0 | M9: =K9*L9 -> 0
B10: UBURO | C10: 500 | D10: 1400 | E10: =C10*D10 -> 700000 | F10: 0 | G10: =G9+E10-SUM(F10) -> 1101600 | I10: =G10*H10 -> 0 | M10: =K10*L10 -> 0
B11: SCOTCH | C11: 15 | D11: 30000 | E11: =D11*C11 -> 450000 | F11: SCOTCH | G11: 10 | H11: 30000 | I11: =G11*H11 -> 300000 | J11: INGANO | K11: 5 | L11: 30000 | M11: =K11*L11 -> 150000
B12: EMBALLAGE | C12: 25000 | D12: 20 | E12: =D12*C12 -> 500000 | I12: =G12*H12 -> 0 | M12: =K12*L12 -> 0
B13: WOODFIX | C13: 100 | D13: 2000 | E13: =D13*C13 -> 200000 | I13: =G13*H13 -> 0 | M13: =K13*L13 -> 0
B14: ISUKARI | C14: 200 | D14: 1600 | E14: =D14*C14 -> 320000 | I14: =G14*H14 -> 0 | M14: =K14*L14 -> 0
B15: AMATA | C15: 40 | D15: 12000 | E15: =D15*C15 -> 480000 | I15: =G15*H15 -> 0 | M15: =K15*L15 -> 0
I16: =G16*H16 -> 0 | M16: =K16*L16 -> 0
M17: =K17*L17 -> 0
E18: =C18*D18 -> 0 | G18: =G17+E18-F18 -> 0 | M18: =K18*L18 -> 0
E19: =C19*D19 -> 0 | G19: =G18+E19-F19 -> 0 | M19: =K19*L19 -> 0
E20: =C20*D20 -> 0 | G20: =G19+E20-F20 -> 0 | M20: =K20*L20 -> 0
E21: =C21*D21 -> 0 | G21: =G20+E21-F21 -> 0 | M21: =K21*L21 -> 0
E22: =SUM(E6:E21) -> 6390000

Sheet APRIL, MAY JUN
B2: AVRIL 2026
A3: date | B3: company tin | C3: company name | D3: items | E3: facture no | F3: vat sent | G3: total amount
A4: 46114 | B4: 103346025 | C4: RIJE LTD | D4: DIFFERENT GOOD | F4: 25627 | G4: 340800
A5: 46114 | C5: FIVE STARSINVESTMENT LTD | D5: SUGER | F5: 983898 | G5: 6450000
A6: 46114 | C6: MINI IMPRIMERIE BLESSING | D6: PAPIER ENVELOPPE | F6: 63457 | G6: 416000
A7: 46116 | C7: QUINCAILLERIE REMARKABLE CO LTD | D7: AKAYUNGIRIZO | F7: 7337 | G7: 48100
A8: 46115 | C8: SP NYIRANGARAMA | D8: ESSANCES | F8: 3052 | G8: 20000
A9: 46115 | C9: SP NYIRANGARAMA | D9: ESSANCES | F9: 8319 | G9: 54538
A10: 46114 | C10: SP NYIRANGARAMA | D10: ESSANCES | F10: 10822 | G10: 70948
A11: 46114 | C11: SP NYIRANGARAMA | D11: ESSANCES | F11: 2311 | G11: 15156
A12: 46113 | C12: SP NYIRANGARAMA | D12: ESSANCES | F12: 3331 | G12: 21838
A13: 46116 | C13: MOUNT MERU PETROLEUM LTD | D13: ESSANCES | F13: 11224 | G13: 73581
A14: 46118 | C14: SP NYIRANGARAMA | D14: ESSANCES | F14: 5037 | G14: 33025 | H14: ISUKARI | I14: 6450000
A15: 46118 | C15: SP NYIRANGARAMA | D15: ESSANCES | F15: 664 | G15: 43688 | I15: 6600000
A16: 46120 | C16: AGRI SOKONI | D16: MAIZE SCREEN | F16: 12203 | G16: 80000 | I16: 3075000
A17: 46118 | C17: POLYBAGS RWANDA | D17: PRINTED BAGS | F17: 24406 | G17: 160000 | H17: IBINYAMPEKE | I17: 275225
A18: 46121 | C18: SP NYIRANGARAMA | D18: ESSANCES | F18: 13451 | G18: 88182 | I18: 913200
A19: 46126 | C19: WELLARS SUPPLY LTD | D19: LUGAZ SUGER | F19: 1006780 | G19: 6600000 | I19: 2300000
A20: 46125 | C20: TERRAZZO LTD | D20: TILES | F20: 8237 | G20: 54000
A21: 46126 | C21: SP NYIRANGARAMA | D21: ESSANCES | F21: 7655 | G21: 50182 | I21: =SUM(I14:I20) -> 19613425
A22: 46122 | C22: SP NYIRANGARAMA | D22: ESSANCES | F22: 11586 | G22: 75953 | H22: SALES | I22: =C49 -> 20459250
A23: 46125 | C23: SP NYIRANGARAMA | D23: ESSANCES | F23: 13118 | G23: 85994
A24: 46125 | C24: VPLUS PACKAGING INDUSTRIES LTD | D24: CARTONS | F24: 273288 | G24: 1791552 | H24: DIFFERENCE | I24: =I21-I22 -> -845825
A25: 46129 | C25: SP NYIRANGARAMA | D25: ESSANCES | F25: 11621 | G25: 76182 | H25: IBITARACURUZWA
A26: 46128 | C26: SP NYIRANGARAMA | D26: ESSANCES | F26: 12028 | G26: 78855
A27: 46121 | C27: SP NYIRANGARAMA | D27: ESSANCES | F27: 4145 | G27: 27175
A28: 46134 | C28: SP NYIRANGARAMA | D28: ESSANCES | F28: 5899 | G28: 38664
A29: 46133 | C29: SP NYIRANGARAMA | D29: ESSANCES | F29: 11105 | G29: 72804
A30: 46135 | C30: SP NYIRANGARAMA | D30: ESSANCES | F30: 4436 | G30: 29086
A31: 46131 | C31: SP NYIRANGARAMA | D31: ESSANCES | F31: 13297 | G31: 87170
A32: 46135 | C32: MINI IMPRIMERIE BLESSING | D32: PAPIER ENVELOPPE | F32: 64067 | G32: 420000
A33: 46120 | C33: COWBE LTD | D33: WATER | F33: 979 | G33: 6422
C34: REG | D34: UMURIRO | F34: 30508 | G34: 200000
A35: 46136 | C35: SP NYIRANGARAMA | D35: ESSANCES | F35: 4100 | G35: 26883
A36: 46139 | C36: MOUNT MERU PETROLEUM LTD | D36: ESSANCES | F36: 18913 | G36: 123984
A37: 46140 | C37: INNOPRO LTD | D37: SUGER | F37: 469068 | G37: 3075000
A38: 46141 | C38: SP NYIRANGARAMA | D38: ESSANCES | F38: 9120 | G38: 59788
A39: 46141 | C39: SP NYIRANGARAMA | D39: ESSANCES | F39: 3809 | G39: 24973
A41: 46121 | C41: NTAGANDA ERASTE | D41: DRIED SORGHUM | G41: 275225
A42: 46122 | C42: HANOCLANO | D42: SORGHUM | G42: =1522*600 -> 913200
A43: 46120 | C43: NTAMUHANGA J BOSCO | D43: IBIGORI | G43: 2300000
A44: 16,17/04/2026 | C44: J BAPTISTE GATABAZI | D44: TRANSPORT | G44: 150000
A45: TOTAL | G45: =SUM(G4:G44) -> 24558948
F46: =SUM(F4:F45) -> 3158898
B47: SALES BRANCH 01 | D47: 19264750 | E47: =D47*18/118 -> 2938690.7
B48: SALES BASE | D48: 1194500 | E48: =D48*18/118 -> 182211.86
C49: =D47+D48 -> 20459250 | E49: =D49*18/118 -> 0
B50: VAT MANAGEMENT | E50: VAT RECEIVED EBM | F50: VAT SENT FACT | G50: VAT TO PAY
B52: VAT BRANCH01 REC | E52: 2938691
B53: VAT BASE REC | E53: 175241
B55: TOTAL | E55: =SUM(E52:E54) -> 3113932 | F55: =F46 -> 3158898 | G55: =E55-F55 -> -44966
G56: WORD
B57: FACTURE ZIKENEWE | E57: =G55*118/18 -> -294777.11
C61: MAI 2026
A62: date | B62: company tin | C62: company name | D62: items | E62: facture no | F62: vat sent | G62: total amount
A63: 46144 | C63: EASTERN HOPE LTD | D63: SUGER | F63: 953390 | G63: 6250000
A64: 46150 | C64: EASTERN HOPE LTD | D64: SUGER | F64: 945762 | G64: 6200000
A65: 46164 | C65: EASTERN HOPE LTD | D65: SUGER | F65: 907627 | G65: 5950000
A66: 46162 | C66: V PLUS PACKAGING INDUSTRIES LTD | D66: CARTONS | F66: 271462 | G66: 1799262
F67: 3081243 | H67: refund 146,504
C68: IZISIGAYE | F68: 3081243 | I68: =F67-F68 -> 0
A69: 46165 | C69: BLUE FLAME | D69: CUISINIERE ELECTRIQUE | F69: 81610 | G69: 535000
A70: 46160 | C70: MINI IMPRIMERIE BLESSINGS LTD | D70: PAPIER ENVELOPPES | F70: 64068 | G70: 420000
C71: REG | D71: UMURIRO | F71: 30508 | G71: 200000
A72: 46159 | C72: SP NYIRANGARAMA | D72: ESSANCES | F72: 14346 | G72: 94045
A73: 46149 | C73: SP NYIRANGARAMA | D73: ESSANCES | F73: 14292 | G73: 93693
A74: 46159 | C74: SP NYIRANGARAMA | D74: ESSANCES | F74: 13364 | G74: 87611
A75: 46159 | C75: SP NYIRANGARAMA | D75: ESSANCES | F75: 13243 | G75: 86818
A76: 46153 | C76: IRIBA TOOLS LTD | D76: TILES | F76: 12630 | G76: 82800
A77: 46170 | C77: SP NYIRANGARAMA | D77: ESSANCES | F77: 12589 | G77: 82528
A78: 46161 | C78: SP NYIRANGARAMA | D78: ESSANCES | F78: 12190 | G78: 79914
A79: 46160 | C79: SP NYIRANGARAMA | D79: ESSANCES | F79: 11944 | G79: 78298
A80: 46168 | C80: SP NYIRANGARAMA | D80: ESSANCES | F80: 10568 | G80: 69278
A81: 46165 | C81: SP NYIRANGARAMA | D81: ESSANCES | F81: 9882 | G81: 64783
A82: 46147 | C82: SP NYIRANGARAMA | D82: ESSANCES | F82: 9555 | G82: 62638
A83: 46171 | C83: SP NYIRANGARAMA | D83: ESSANCES | F83: 8694 | G83: 56997
... A91: 46151 | C91: SP NYIRANGARAMA | D91: ESSANCES | F91: 5194 | G91: 34051
C92: UNKOWN | F92: 27593 | G92: 180900
A93: 46150 | C93: PRODEV RWANDA SARL | D93: LAYERS MASH | G93: 76500
A94: 46149 | C94: NTAGANDA ERASTE | D94: DRIED SORHUM | G94: 50500
A95: 46149 | C95: NTAGANDA ERASTE | D95: DRIED SORHUM | G95: 505000
A96: 46160 | C96: NTAGANDA ERASTE | D96: DRIED SORHUM | G96: 494900
A97: 46157 | C97: BATTISTA BUSINESS LTD | D97: SOYA IBIGORI | G97: 2400000
B101: SALES BRANCH 01 | D101: 18429550 | E101: =D101*18/118 -> 2811287.3 | H101: STOCK
B102: SALES BASE | D102: 865800 | E102: 136494 | F102: 0
C103: =D101+D102 -> 19295350 | D103: 180900 | E103: =D103*18/118 -> 27594.915 | F103: =F67 -> 3081243
B104: VAT MANAGEMENT | E104: VAT RECEIVED EBM | F104: VAT SENT FACT | G104: VAT TO PAY | J104: =H106-F109 -> 402610
B106: VAT BRANCH01 REC | E106: 2811287 | H106: 3483853
B107: VAT BASE REC | E107: 123453
B109: TOTAL | E109: =SUM(E106:E108) -> 2934740 | F109: =F103 -> 3081243 | G109: =E109-F109 -> -146503 | H109: REFUND
G110: WORD
B111: FACTURE ZIKENEWE | C111: 46173 | E111: =G109*118/18 -> -960408.56
B113: JUN
A114: date | B114: company tin | C114: company name | D114: items | E114: facture no | F114: vat sent | G114: total amount
A115: 46186 | C115: KAMU KAMU TRADING | D115: SUGER | F115: 930508 | G115: 6100000
A116: 46186 | C116: INNOPRO LTD | D116: SUGER | F116: 930508 | G116: 6100000
A117: 46191 | C117: EASTERN HOPE | D117: SUGER | F117: 915254 | G117: 6000000
A118: 46202 | C118: INNOPRO LTD | D118: SUGER | F118: 186101 | G118: 1220000
F119: =SUM(F115:F118) -> 2962371 | G119: =SUM(G115:G118) -> 19420000 | H119: REFUND 277,473
C120: IZISIGAYE
...

Sheet JULY AUG SEPT 
B2: 46204
A3: date | B3: company tin | C3: company name | D3: items | E3: vat sent | F3: total amount
A4: 46205 | C4: VPLUS PACKAGING INDUSTRIES LTD | D4: CARTONS | E4: 277030 | F4: 1816084
A5: 46204 | C5: SP NYIRANGARAMA | D5: ESSANCES | E5: 16277 | F5: 106708
A6: 46205 | C6: SP NYIRANGARAMA | D6: ESSANCES | E6: 4576 | F6: 30000
A7: 46206 | C7: PEACE H TRADING COMPANY LTD | D7: COLLE WOODFIX | E7: 15254 | F7: 100000
A8: 46206 | C8: SP NYIRANGARAMA | D8: ESSANCES | E8: 16736 | F8: 109705
A9: 46209 | C9: SP NYIRANGARAMA | D9: ESSANCES | E9: 14270 | F9: 93546
A10: 46210 | C10: SP NYIRANGARAMA | D10: ESSANCES | E10: 15309 | F10: 100362
A11: 46214 | C11: MOUNT MERU PETROLEUM | D11: ESSANCES | E11: 6973 | F11: 45715
A12: 46213 | C12: SP NYIRANGARAMA | D12: ESSANCES | E12: 15968 | F12: 104681
A13: 46210 | C13: POLYBAGS RWANDA LTD | D13: BAGS | E13: 28220 | F13: 185000
A14: 46216 | C14: GILGAL LTD | D14: BANDEFREI | E14: 7780 | F14: 51000
A15: 46216 | C15: SP NYIRANGARAMA | D15: ESSANCES | E15: 9618 | F15: 63049
... A26: 46217 | C26: BFBMS LTD | D26: BRAKE PAD | E26: 3050 | F26: 20000
A32: 46206 | C32: PRODEV RWANDA LTD | D32: LAYERS MASH | F32: 116000
A33: 46210 | C33: PRODEV RWANDA LTD | D33: LAYERS MASH | F33: 78500
A34: 46207 | C34: NTAGANDA ERASTE | D34: SORGHUM | F34: 748410
A35: 46216 | C35: NTAGANDA ERASTE | D35: SORGHUM | F35: 571155
A36: 46213 | C36: PRODEV RWANDA LTD | D36: LAYERS MASH | F36: 116000
A37: 46217 | C37: PRODEV RWANDA LTD | D37: GROWER MASH | F37: 37500
E46: =SUM(E4:E40) -> 1488556
B47: SALES BRANCH 01 | D47: 10198500 | E47: =D47*18/118 -> 1555703.4
B48: SALES BASE | D48: 572000 | E48: =D48*18/118 -> 87254.237
C49: =D47+D48 -> 10770500 | E49: =D49*18/118 -> 0
B50: VAT MANAGEMENT | E50: VAT SENT FACT | F50: VAT TO PAY
B52: VAT BRANCH01 REC | D52: 1555703
B53: VAT BASE REC | D53: 87254
B55: TOTAL | D55: =SUM(D52:D54) -> 1642957 | E55: =E46 -> 1488556 | F55: =D55-E55 -> 154401 | H55: AYISHYURWA
F56: WORD | H56: BURI KWEZI
B57: FACTURE ZIKENEWE | D57: =F55*118/18 -> 1012184.3
C61: MAI 2026
A62: date | B62: company tin | C62: company name | D62: items | E62: vat sent | F62: total amount
H68: =E67-E68 -> 0
A90: IBINYAMPEKE BIDAFITE VAT
B101: SALES BRANCH 01 | D101: 18429550 | G101: STOCK
B102: SALES BASE | D102: 865800 | E102: 0
C103: =D101+D102 -> 19295350 | D103: 180900 | E103: =E67 -> 0
B104: VAT MANAGEMENT | E104: VAT SENT FACT | F104: VAT TO PAY | I104: =G106-E109 -> 3483853
B106: VAT BRANCH01 REC | D106: =D101*18/118 -> 2811287.3 | G106: 3483853
B107: VAT BASE REC | D107: =D102*18/118 -> 132071.19 | G107: J
B109: TOTAL | D109: =SUM(D106:D108) -> 2943358.5 | E109: =E103 -> 0 | F109: =D109-E109 -> 2943358.5
F110: WORD
B111: FACTURE ZIKENEWE | C111: 46173
B113: JUN
A114: date | B114: company tin | C114: company name | D114: items | E114: vat sent | F114: total amount
A115: 46174 | C115: MOUNT MERU PETROLIUM | D115: ESSANCES | E115: 15614 | F115: 102360
A116: 46175 | C116: SP NYIRANGARAMA | D116: ESSANCES | E116: 12558 | F116: 82323
A117: 46182 | C117: IRIBA TOOLS LTD | D117: TILES | E117: 22881 | F117: 150000
A118: 46182 | C118: SP NYIRANGARAMA | D118: ESSANCES | E118: 10070 | F118: 66017
A119: 46183 | C119: SP NYIRANGARAMA | D119: ESSANCES | E119: 3052 | F119: 20000
A120: 46178 | C120: BFBMS LTS | D120: SHOK ABSOLBER SP | E120: 3813 | F120: 25000
A121: 46177 | C121: SP NYIRANGARAMA | D121: ESSANCES | E121: 9528 | F121: 62462
A122: 46178 | C122: SP NYIRANGARAMA | D122: ESSANCES | E122: 10769 | F122: 70600
A123: 42530 | C123: SP NYIRANGARAMA | D123: ESSANCES | E123: 4576 | F123: 30000
A124: 46186 | C124: KAMU KAMU TRADING | D124: SUGER | E124: 930508 | F124: 6100000
A125: 46188 | C125: SP NYIRANGARAMA | D125: ESSANCES | E125: 7560 | F125: 49564
A126: 46185 | C126: SP NYIRANGARAMA | D126: ESSANCES | E126: 7910 | F126: 51856
... A154: 46203 | C154: EUCL | D154: ELECTRICITY | E154: 15216 | F154: 100000
A158: 46174 | C158: PROGRESS 250 LTD | D158: AMASAKA | F158: 250000
A159: 46174 | C159: LIFELINE LTD | D159: HAELTH CARE | F159: 70000
A160: 46174 | C160: VETLINKS LTS | D160: TOTAL AFLATOXIN RAPID TEST | F160: 250000
A161: 46178 | C161: PRODEV RWANDA SARL | D161: LAYERS MASH | F161: 115500
A162: 46106 | C162: RAMICO LTD | D162: BLANDA IBIGORI | F162: 22100
A163: 46185 | C163: PRODEV RWANDA SARL | D163: LAYERS MASH | F163: 76500
A164: 46184 | C164: PROGRESS 250 LTD | D164: AMASAKA | F164: 797500
A165: 46190 | C165: PRODEV RWANDA SARL | D165: PULLET STARTER MASH | F165: 115500
A166: 46199 | C166: ALENIKA GROUP TRADING | D166: AKAYUNGURUZO | F166: 20000
A167: 46198 | C167: NTAGANDA ERASTE | D167: AMASAKA | F167: 527220
B168: SALES BRANCH 01 | D168: 16477000
B169: SALES BASE | D169: 1200000
C170: =D168+D169 -> 17677000 | E170: =SUM(E115:E169) -> 2406698
B171: VAT MANAGEMENT | E171: VAT SENT FACT | F171: VAT TO PAY
B173: VAT BRANCH01 REC | D173: =D168*18/118 -> 2513440.7
B174: VAT BASE REC | D174: =D169*18/118 -> 183050.85
B176: TOTAL | D176: =SUM(D173:D175) -> 2696491.5 | E176: =E170 -> 2406698 | F176: =D176-E176 -> 289793.53
F177: 146503
B178: FACTURE ZIKENEWE | F178: =F176-F177 -> 143290.53
B180: MARS 2026
B215: SALES BRANCH 01 | D215: 19789250
B216: SALES BASE | D216: 1805900
C217: =D215+D216 -> 21595150 | E217: =SUM(E181:E216) -> 0
B218: VAT MANAGEMENT | E218: VAT SENT FACT | F218: VAT TO PAY
B220: VAT BRANCH01 REC | D220: =D215*18/118 -> 3018699.2
B221: VAT BASE REC | D221: =D216*18/118 -> 275476.27
B223: TOTAL | D223: =SUM(D220:D222) -> 3294175.4 | E223: =E217 -> 0 | F223: =D223-E223 -> 3294175.4
C224: 46106
B225: FACTURE ZIKENEWE
F350: =SUM(F279:F349) -> 0

Sheet OCT NOV DEC

Sheet ANNUAL REPORT
A1: 46039 | C1: PLAN ONE SUPPLY LTD | D1: IBIKORESHO BYO KUBAKA | F1: 508576 | G1: 3334000
A2: 46044 | C2: MINI IMPRIMERIES BLESSING | D2: PAPIER ENVELOPPES | F2: 62542 | G2: 410000
A3: 46038 | C3: MINI IMPRIMERIES BLESSING | D3: PAPIER ENVELOPPES | F3: 46067 | G3: 302000
A4: 46028 | C4: REG | D4: UMURIRO | E4: 50000 | F4: 30508 | G4: 200000
A5: 45670 | C5: RIJE LTD | D5: DIFFERENT GOODS | F5: 25916 | G5: 200000
A6: 46032 | C6: MINI IMPRIMERIES BLESSING | D6: PAPIER ENVELOPPES | F6: 22729 | G6: 149000
A7: 46041 | C7: CPS LUBRICANT LTD | D7: HELIOS SAE | F7: 18305 | G7: 120000
A8: 46027 | C8: AKOMBONYE COMPANY LTD | D8: WOODFIX | F8: 12600 | G8: 82600
A9: 46050 | C9: CHAMPION TECHNOLOGIES LTD | D9: INK | F9: 1220 | G9: 8000
A10: 46042 | C10: IKAMBA GENERAL TRADING &SUPPLY CO LTD | D10: PRINT CERTIFICATES | F10: 6102 | G10: 40000
A11: 46050 | C11: REG | D11: UMURIRO | F11: 3043 | G11: 20000
A12: 46029 | C12: AGRUNI LTD | D12: WASTE COLLECTION SRV | G12: 24000
A13: 46035 | C13: SP NYIRANGARAMA | D13: ESSANCES | F13: 11180 | G13: 73295
A14: 46043 | C14: SP NYIRANGARAMA | D14: ESSANCES | F14: 10825 | G14: 70968
A15: 46027 | B15: 103582274 | C15: SP NYIRANGARAMA | D15: ESSANCES | F15: 10312 | G15: 67606
A16: 46032 | C16: SP NYIRANGARAMA | D16: ESSANCES | F16: 9867 | G16: 64682
A17: 46037 | C17: SP NYIRANGARAMA | D17: ESSANCES | F17: 9660 | G17: 63330
A18: 46039 | C18: SP NYIRANGARAMA | D18: ESSANCES | F18: 9226 | G18: 60485
A19: 46049 | C19: SP NYIRANGARAMA | D19: ESSANCES | F19: 8428 | G19: 55254
A20: 46029 | C20: SP NYIRANGARAMA | D20: ESSANCES | F20: 8049 | G20: 52768
A21: 46028 | C21: SP NYIRANGARAMA | D21: ESSANCES | F21: 7958 | G21: 52171
A22: 46030 | C22: SP NYIRANGARAMA | D22: ESSANCES | F22: 7833 | G22: 51356
A23: 46034 | C23: SP NYIRANGARAMA | D23: ESSANCES | F23: 6899 | G23: 45230
A24: 46051 | C24: SP NYIRANGARAMA | D24: ESSANCES | F24: 6884 | G24: 45130
A25: 46025 | B25: 103582274 | C25: SP NYIRANGARAMA | D25: ESSANCES | F25: 6762 | G25: 44335
A26: 46039 | C26: SP NYIRANGARAMA | D26: ESSANCES | F26: 6733 | G26: 44136
A27: 46024 | B27: 103582274 | C27: SP NYIRANGARAMA | D27: ESSANCES | F27: 6374 | G27: 41769
A28: 46031 | C28: SP NYIRANGARAMA | D28: ESSANCES | F28: 5252 | G28: 34430
A29: 46037 | C29: SP NYIRANGARAMA | D29: ESSANCES | F29: 4575 | G29: 30000
A30: 46050 | C30: SP NYIRANGARAMA | D30: ESSANCES | F30: 4554 | G30: 29855
A31: 46050 | C31: SP NYIRANGARAMA | D31: ESSANCES | F31: 4554 | G31: 29855
A32: 46034 | C32: SP NYIRANGARAMA | D32: ESSANCES | F32: 3052 | G32: 20000
A33: 46040 | C33: SP NYIRANGARAMA | D33: ESSANCES | F33: 2833 | G33: 18577
A34: 46036 | C34: SP NYIRANGARAMA | D34: ESSANCES | F34: 1526 | G34: 10000
A35: 46030 | C35: BATTISTA BUSINESS | D35: IBIGORI | G35: 4040000
A36: 46043 | C36: BATTISTA BUSINESS | D36: SOYA NÍBIGORI | G36: 5200000
A37: 46043 | C37: GACAMUMANZA | D37: IBIGORI | G37: 1435000
A38: 46029 | C38: MAGENDU PONTIEN | D38: IBIGORI | G38: 2000000
G39: =SUM(G1:G38) -> 18569832
B40: IZISIGAYE FEVRUARY 2026
A41: 46055 | B41: RWEMA AGRI BUSINESS | C41: URUDODO | F41: 21000
A42: 46059 | B42: BATTISTA BUSINESS LTD | C42: IBIGORI SOYA | F42: 4850000
A43: 46066 | B43: BATTISTA BUSINESS LTD | C43: IBIGORI SOYA | F43: 4650000
A44: 46064 | B44: NTAGANDA ERASTE | C44: AMASAKA | F44: 757500
A45: 46065 | B45: NTAGANDA ERASTE | C45: AMASAKA | F45: 757000
A46: 46069 | B46: ANGE FAMILY BUSINESS COMPANY LTD | C46: UBURO | F46: 100000
A47: 46072 | B47: SERAGRAMS LTD | C47: SOYA | F47: 429300
F48: =SUM(F41:F47) -> 11564800
B49: IZISIGAYE MARS 2026
A50: 119558986 | B50: PLAN ONE SUPPLY Ltd | C50: DIFFERENT GOODS | D50: SDC010016580/24093 | E50: 46097 | F50: 127118.64 | G50: 22881.36
A51: 106553798 | B51: CENTOR Ltd | C51: DIFFERENT GOODS | D51: SDC010003976/28704 | E51: 46095 | F51: 610169.49 | G51: 109830.51
A52: 102364950 | B52: GILGAL Ltd | C52: DIFFERENT GOODS | D52: SDC007068945/34982 | E52: 46083 | F52: 38983.05 | G52: 7016.95
A53: 101490013 | B53: HATUNGURAMYE | C53: DIFFERENT GOODS | D53: SDC010082516/3804 | E53: 46083 | F53: 72881.36 | G53: 13118.64
F54: 152847 | G54: =SUM(G50:G53) -> 152847.46
A55: 110101631 | B55: NTAGANDA ERASTE | C55: DIFFERENT GOODS | D55: SDC010035518/7001 | E55: 46104 | F55: 808000 | G55: 0
A56: 46092 | B56: NTAGANDA ERASTE | C56: AMASAKA | F56: 808000
A57: 46094 | B57: ISARO MAIZE COMPANY LTD | C57: ISARO MAIZE FLOUR | F57: 400000
A58: 46112 | B58: BATTISTA BUSINESS LTD | C58: IBIGORI | F58: 4200000
F59: =SUM(F50:F53)+SUM(F55:F58) -> 7065152.5
B60: IZISIGAYE AVRIL 2026
A61: 103582274 | B61: SINA GERARD PETROLEUM (SIGEPE) Ltd | C61: DIFFERENT GOODS | D61: SDC014000881/147028 | E61: 46113 | F61: 18507.82 | G61: 3331.4
A62: 103582274 | B62: SINA GERARD PETROLEUM (SIGEPE) Ltd | C62: DIFFERENT GOODS | D62: SDC014000881/147356 | E62: 46114 | F62: 12844.23 | G62: 2311.95
A63: 103582274 | B63: SINA GERARD PETROLEUM (SIGEPE) Ltd | C63: DIFFERENT GOODS | D63: SDC014000881/147416 | E63: 46114 | F63: 60125.12 | G63: 10822.51
A64: 103582274 | B64: SINA GERARD PETROLEUM (SIGEPE) Ltd | C64: DIFFERENT GOODS | D64: SDC014000881/147678 | E64: 46115 | F64: 46218.97 | G64: 8319.41
A65: 103582274 | B65: SINA GERARD PETROLEUM (SIGEPE) Ltd | C65: DIFFERENT GOODS | D65: SDC014000881/147932 | E65: 46115 | F65: 16957.07 | G65: 3052.27
A66: 103582274 | B66: SINA GERARD PETROLEUM (SIGEPE) Ltd | C66: DIFFERENT GOODS | D66: SDC014000881/148774 | E66: 46118 | F66: 27987.31 | G66: 5037.71
A67: 103582274 | B67: SINA GERARD PETROLEUM (SIGEPE) Ltd | C67: DIFFERENT GOODS | D67: SDC014000881/149496 | E67: 46121 | F67: 74730.4 | G67: 13451.47
A68: 103582274 | B68: SINA GERARD PETROLEUM (SIGEPE) Ltd | C68: DIFFERENT GOODS | D68: SDC014000881/149561 | E68: 46121 | F68: 23030 | G68: 4145.4
A69: 103582274 | B69: SINA GERARD PETROLEUM (SIGEPE) Ltd | C69: DIFFERENT GOODS | D69: SDC014000881/149677 | E69: 46122 | F69: 64366.9 | G69: 11586.04
A70: 103582274 | B70: SINA GERARD PETROLEUM (SIGEPE) Ltd | C70: DIFFERENT GOODS | D70: SDC014000881/150337 | E70: 46125 | F70: 72876.29 | G70: 13117.73
A71: 103582274 | B71: SINA GERARD PETROLEUM (SIGEPE) Ltd | C71: DIFFERENT GOODS | D71: SDC014000881/150574 | E71: 46126 | F71: 42527.44 | G71: 7654.93
A72: 103582274 | B72: SINA GERARD PETROLEUM (SIGEPE) Ltd | C72: DIFFERENT GOODS | D72: SDC014000881/151037 | E72: 46128 | F72: 66826.04 | G72: 12028.68
A73: 103582274 | B73: SINA GERARD PETROLEUM (SIGEPE) Ltd | C73: DIFFERENT GOODS | D73: SDC014000881/151123 | E73: 46128 | F73: 26874.84 | G73: 4837.47
B74: IZANZE | F74: 99697 | G74: =SUM(G61:G73) -> 99696.97
A75: 101419165 | B75: JEAN BAPTISTE GATABAZI | C75: DIFFERENT GOODS | D75: SDC010148477/351 | E75: 46114 | F75: 50000
A76: 101419165 | B76: JEAN BAPTISTE GATABAZI | C76: DIFFERENT GOODS | D76: SDC010148477/397 | E76: 46128 | F76: 50000
A77: 101419165 | B77: JEAN BAPTISTE GATABAZI | C77: DIFFERENT GOODS | D77: SDC010148477/399 | E77: 46129 | F77: 50000
A78: 101419165 | B78: JEAN BAPTISTE GATABAZI | C78: DIFFERENT GOODS | D78: SDC010148477/414 | E78: 46141 | F78: 50000
A79: 102419403 | B79: JEAN BOSCO NTAMUHANGA | C79: DIFFERENT GOODS | D79: SDC010059385/60 | E79: 46120 | F79: 2300000
A80: 122310009 | B80: BATTISTA BUSINESS Ltd | C80: DIFFERENT GOODS | D80: SDC010084409/686 | E80: 46119 | F80: 6850000
A81: 110101631 | B81: NTAGANDA ERASTE | C81: DIFFERENT GOODS | D81: SDC010035518/7072 | E81: 46121 | F81: 275225
A82: 110101631 | B82: NTAGANDA ERASTE | C82: DIFFERENT GOODS | D82: SDC010035518/7128 | E82: 46135 | F82: 505000
A84: 46121 | C84: NTAGANDA ERASTE | D84: DRIED SORGHUM | F84: 275225
A85: 46122 | C85: HANOCLANO | D85: SORGHUM | F85: =1522*600 -> 913200
F86: =SUM(F61:F73)+SUM(F75:F85) -> 11872522
B87: IZASIGAYE MAY 2026
A88: Supplier TIN | B88: Supplier name | C88: Nature of Goods | D88: Receipt number | E88: Receipt issue date | F88: Amount without VAT | G88: VAT
A89: 108604962 | B89: BLUEFLAME Ltd | C89: DIFFERENT GOODS | D89: SDC007070336/6065 | E89: 46165 | F89: 453389.83 | G89: 81610.17
A90: 101899340 | B90: MINI IMPRIMERIE "BLESSING" LTD | C90: DIFFERENT GOODS | D90: SDC010113591/569 | E90: 46160 | F90: 355932.2 | G90: 64067.8
A91: 105330055 | B91: IRIBA TOOLS Ltd | C91: DIFFERENT GOODS | D91: SDC010034219/9871 | E91: 46164 | F91: 227203.39 | G91: 40896.61
A92: 103582274 | B92: SINA GERARD PETROLEUM (SIGEPE) Ltd | C92: DIFFERENT GOODS | D92: SDC014000881/156290 | E92: 46159 | F92: 79699.48 | G92: 14345.9
A93: 103582274 | B93: SINA GERARD PETROLEUM (SIGEPE) Ltd | C93: DIFFERENT GOODS | D93: SDC014000881/155205 | E93: 46149 | F93: 79400.7 | G93: 14292.12
A94: 103582274 | B94: SINA GERARD PETROLEUM (SIGEPE) Ltd | C94: DIFFERENT GOODS | D94: SDC014000881/156937 | E94: 46159 | F94: 74246.75 | G94: 13364.41
A95: 103582274 | B95: SINA GERARD PETROLEUM (SIGEPE) Ltd | C95: DIFFERENT GOODS | D95: SDC014000881/156696 | E95: 46159 | F95: 73574.5 | G95: 13243.4
A96: 105330055 | B96: IRIBA TOOLS Ltd | C96: DIFFERENT GOODS | D96: SDC010034219/9784 | E96: 46153 | F96: 70169.49 | G96: 12630.51
A97: 103582274 | B97: SINA GERARD PETROLEUM (SIGEPE) Ltd | C97: DIFFERENT GOODS | D97: SDC014000881/159574 | E97: 46170 | F97: 69939.34 | G97: 12589.08
A98: 103582274 | B98: SINA GERARD PETROLEUM (SIGEPE) Ltd | C98: DIFFERENT GOODS | D98: SDC014000881/157647 | E98: 46161 | F98: 67723.39 | G98: 12190.21
A99: 103582274 | B99: SINA GERARD PETROLEUM (SIGEPE) Ltd | C99: DIFFERENT GOODS | D99: SDC014000881/157369 | E99: 46160 | F99: 66353.99 | G99: 11943.71
A100: 103582274 | B100: SINA GERARD PETROLEUM (SIGEPE) Ltd | C100: DIFFERENT GOODS | D100: SDC014000881/159071 | E100: 46168 | F100: 58710.21 | G100: 10567.83
... A113: 103582274 | B113: SINA GERARD PETROLEUM (SIGEPE) Ltd | C113: DIFFERENT GOODS | D113: SDC014000881/156758 | E113: 46159 | F113: 23279.92 | G113: 4190.38
...

Sheet UNCONTROLED 
B4: 1 | C4: INYUNGU KU NGUZANYO
B5: 2 | C5: DEPENSES Z
B6: 3 | C6: DEPRECIATION IMODOKA NA MACHINE
B7: 4 | C7: UBUKODE BW'INZU | D7: =30000*12 -> 360000
B8: 5 | C8: PARKING YÍMODOKA MU MUJYI
B9: 6 | C9: GUKANIKA IMODOKA
B10: 7 | C10: GUHAHA IBIRIBWA BYÁBAKOZI (IBITOKI, IBIRAYI, AMASHU, AMATA, IMYUMBATI, AMATEKE, INKA, IHENE, INGURUBE, INTAMA,
B11: 8 | C11: GUHAHA INKA,
B12: 9 | C12: UMUTEKANO
